construct_editor/__init__.py
construct_editor/main.py
construct_editor/py.typed
construct_editor/version.py
construct_editor/core/__init__.py
construct_editor/core/callbacks.py
construct_editor/core/commands.py
construct_editor/core/construct_editor.py
construct_editor/core/context_menu.py
construct_editor/core/custom.py
construct_editor/core/entries.py
construct_editor/core/model.py
construct_editor/core/preprocessor.py
construct_editor/gallery/__init__.py
construct_editor/gallery/example_cmd_resp.py
construct_editor/gallery/example_ipstack.py
construct_editor/gallery/example_pe32coff.py
construct_editor/gallery/test_aligned.py
construct_editor/gallery/test_array.py
construct_editor/gallery/test_bits_swapped_bitwise.py
construct_editor/gallery/test_bitwise.py
construct_editor/gallery/test_bytes_greedybytes.py
construct_editor/gallery/test_checksum.py
construct_editor/gallery/test_compressed.py
construct_editor/gallery/test_computed.py
construct_editor/gallery/test_const.py
construct_editor/gallery/test_dataclass_bit_struct.py
construct_editor/gallery/test_dataclass_struct.py
construct_editor/gallery/test_enum.py
construct_editor/gallery/test_fixedsized.py
construct_editor/gallery/test_flag.py
construct_editor/gallery/test_flagsenum.py
construct_editor/gallery/test_focusedseq.py
construct_editor/gallery/test_greedyrange.py
construct_editor/gallery/test_ifthenelse.py
construct_editor/gallery/test_ifthenelse_nested_switch.py
construct_editor/gallery/test_nullstripped.py
construct_editor/gallery/test_nullterminated.py
construct_editor/gallery/test_padded.py
construct_editor/gallery/test_padded_string.py
construct_editor/gallery/test_pass.py
construct_editor/gallery/test_pointer_peek_seek_tell.py
construct_editor/gallery/test_renamed.py
construct_editor/gallery/test_select.py
construct_editor/gallery/test_select_complex.py
construct_editor/gallery/test_stringencodded.py
construct_editor/gallery/test_switch.py
construct_editor/gallery/test_switch_dataclass.py
construct_editor-0.1.5.dist-info/LICENSE
construct_editor-0.1.5.dist-info/METADATA
construct_editor-0.1.5.dist-info/WHEEL
construct_editor-0.1.5.dist-info/entry_points.txt
construct_editor-0.1.5.dist-info/top_level.txt
construct_editor-0.1.5.dist-info/RECORD
