Metadata-Version: 2.1
Name: construct-editor
Version: 0.1.5
Summary: GUI (based on wxPython) for 'construct', which is a powerful declarative and symmetrical parser and builder for binary data.
Home-page: https://github.com/timrid/construct-editor
Author: Tim Riddermann
License: MIT
Keywords: gui,wx,wxpython,widget,binary,editorconstruct,kaitai,declarative,data structure,struct,binary,symmetric,parser,builder,parsing,building,pack,unpack,packer,unpacker,bitstring,bytestring,bitstruct
Platform: Windows
Classifier: Development Status :: 3 - Alpha
Classifier: License :: OSI Approved :: MIT License
Classifier: Programming Language :: Python :: 3
Classifier: Programming Language :: Python :: 3.8
Classifier: Programming Language :: Python :: 3.9
Classifier: Programming Language :: Python :: 3.10
Classifier: Programming Language :: Python :: 3.11
Classifier: Programming Language :: Python :: Implementation :: CPython
Classifier: Typing :: Typed
Requires-Python: >=3.8
License-File: LICENSE
Requires-Dist: construct (==2.10.68)
Requires-Dist: construct-typing (==0.6.*)
Requires-Dist: wxPython (>=4.1.1)
Requires-Dist: arrow (>=1.0.0)
Requires-Dist: wrapt (>=1.14.0)
Requires-Dist: typing-extensions (>=4.4.0)
